LICENSE
dictionaries/warodai.jtdb
dictionaries/yarxi.jtdb
jrsub/__init__.py
jrsub/entry.py
jrsub/reference.py
jrsub/search.py
jrsub/utils.py
jrsub/warodai.py
jrsub/yarxi.py
jrsub-0.1.11.dist-info/METADATA
jrsub-0.1.11.dist-info/WHEEL
jrsub-0.1.11.dist-info/LICENSE
jrsub-0.1.11.dist-info/RECORD
